mongodb_test_package/__init__.py
mongodb_test_package/mongo_crud.py
MongoTestFirst-0.0.6.dist-info/LICENSE
MongoTestFirst-0.0.6.dist-info/METADATA
MongoTestFirst-0.0.6.dist-info/WHEEL
MongoTestFirst-0.0.6.dist-info/top_level.txt
MongoTestFirst-0.0.6.dist-info/RECORD
